pagekey_docgen/__init__.py
pagekey_docgen/__main__.py
pagekey_docgen/cli.py
pagekey_docgen/config.py
pagekey_docgen/core.py
pagekey_docgen/templates/Makefile
pagekey_docgen/templates/conf.py
pagekey_docgen/templates/make.bat
pagekey_docgen-1.0.3.dist-info/METADATA
pagekey_docgen-1.0.3.dist-info/WHEEL
pagekey_docgen-1.0.3.dist-info/entry_points.txt
pagekey_docgen-1.0.3.dist-info/RECORD
